model_import_export/__init__.py
model_import_export/apps.py
model_import_export/resources.py
model_import_export-0.1.4.dist-info/LICENSE
model_import_export-0.1.4.dist-info/METADATA
model_import_export-0.1.4.dist-info/WHEEL
model_import_export-0.1.4.dist-info/top_level.txt
model_import_export-0.1.4.dist-info/RECORD
