Metadata-Version: 2.1
Name: model-import-export
Version: 0.1.4
Summary: Import/Export feature for django models
Home-page: https://github.com/aj3sh/model_import_export
Author: Ajesh Sen Thapa
Author-email: aj3sshh@gmail.com
License: UNKNOWN
Platform: UNKNOWN
Classifier: Environment :: Web Environment
Classifier: Framework :: Django
Classifier: Framework :: Django :: 1.11
Classifier: Framework :: Django :: 2.0
Classifier: Framework :: Django :: 2.1
Classifier: Programming Language :: Python :: 3
Classifier: License :: OSI Approved :: MIT License
Classifier: Operating System :: OS Independent
Requires-Dist: numpy
Requires-Dist: pandas
Requires-Dist: python-dateutil
Requires-Dist: pytz
